{
	"Name": "Stardew Aquarium Trophy",
	"Price": 1,
	"Description": "Rewarded for helping the Stardew Aquarium reach its full potential!",
	"ProvidesLight": false,
	"NameLocalization": {
		/*"es": "", //Spansih
		"ko": "", //Korean
		"de": "", //German
		"fr": "", //French
		"hu": "", //Hungarian
		"it": "", //Italian
		"ja": "", //Japanese
		"pt": "", //Portuguese
		"ru": "", //Russian
		"tr": "", //Turkish*/
		"zh": "星露水族馆奖杯"
	},
	"DescriptionLocalization": {
		/*"es": "", //Spansih
		"ko": "", //Korean
		"de": "", //German
		"fr": "", //French
		"hu": "", //Hungarian
		"it": "", //Italian
		"ja": "", //Japanese
		"pt": "", //Portuguese
		"ru": "", //Russian
		"tr": "", //Turkish*/
		"zh": "因协助水族馆而获得奖励"
	}
}